simple_prompts_mcp/__init__.py
simple_prompts_mcp/__main__.py
simple_prompts_mcp/exceptions.py
simple_prompts_mcp/get_prompt.py
simple_prompts_mcp/list_prompts.py
simple_prompts_mcp/models.py
simple_prompts_mcp/server.py
simple_prompts_mcp/utils.py
simple_prompts_mcp-0.1.1.dist-info/METADATA
simple_prompts_mcp-0.1.1.dist-info/WHEEL
simple_prompts_mcp-0.1.1.dist-info/entry_points.txt
simple_prompts_mcp-0.1.1.dist-info/licenses/LICENSE
simple_prompts_mcp-0.1.1.dist-info/RECORD
