Metadata-Version: 2.4
Name: simple-prompts-mcp
Version: 0.1.1
Summary: Simple Prompt MCP Server
Project-URL: Homepage, https://github.com/sinofseven/simple-prompts-mcp
Project-URL: Issues, https://github.com/sinofseven/simple-prompts-mcp/issues
Author-email: sinofseven <em.s.00001@gmail.com>
License: MIT
License-File: LICENSE
Requires-Python: >=3.11
Requires-Dist: mcp[cli]==1.8.1
Requires-Dist: pydantic-settings==2.9.1
Requires-Dist: pydantic==2.11.4
Requires-Dist: pyyaml==6.0.2
